smart_hashmap/__init__.py
smart_hashmap/action.py
smart_hashmap/cache.py
smart_hashmap/index.py
smart_hashmap-1.0.4.dist-info/LICENSE
smart_hashmap-1.0.4.dist-info/METADATA
smart_hashmap-1.0.4.dist-info/WHEEL
smart_hashmap-1.0.4.dist-info/top_level.txt
smart_hashmap-1.0.4.dist-info/RECORD
