Metadata-Version: 2.1
Name: smart-hashmap
Version: 1.0.4
Summary: Wrapper for hash map based storage systems
Home-page: https://github.com/yurzs/smart_hashmap
Author: Yury Sokov aka. Yurzs
Author-email: yurzs+smart_hashmap@icloud.com
License: MIT
Keywords: cache,indexes
Platform: UNKNOWN
Classifier: Development Status :: 3 - Alpha
Classifier: License :: OSI Approved :: MIT License
Classifier: Programming Language :: Python :: 3.6
Classifier: Programming Language :: Python :: 3.7
Classifier: Programming Language :: Python :: 3.8
Classifier: Programming Language :: Python :: 3.9
